.csslintrc
.editorconfig
.gitignore
.jshintignore
.travis.yml
CHANGES.rst
MANIFEST.in
README.rst
bootstrap.py
buildout.cfg
setup.cfg
setup.py
travis.cfg
docs/README
docs/_images/README
docs/source/conf.py
docs/source/configuration.rst
docs/source/index.rst
docs/source/_static/logo.png
docs/source/_templates/empty
src/ps/__init__.py
src/ps.fonts.iconmagic.egg-info/PKG-INFO
src/ps.fonts.iconmagic.egg-info/SOURCES.txt
src/ps.fonts.iconmagic.egg-info/dependency_links.txt
src/ps.fonts.iconmagic.egg-info/entry_points.txt
src/ps.fonts.iconmagic.egg-info/namespace_packages.txt
src/ps.fonts.iconmagic.egg-info/not-zip-safe
src/ps.fonts.iconmagic.egg-info/requires.txt
src/ps.fonts.iconmagic.egg-info/top_level.txt
src/ps/fonts/__init__.py
src/ps/fonts/iconmagic/__init__.py
src/ps/fonts/iconmagic/config.py
src/ps/fonts/iconmagic/configure.zcml
src/ps/fonts/iconmagic/interfaces.py
src/ps/fonts/iconmagic/migration.py
src/ps/fonts/iconmagic/profiles.zcml
src/ps/fonts/iconmagic/setuphandlers.py
src/ps/fonts/iconmagic/testing.py
src/ps/fonts/iconmagic/Extensions/install.py
src/ps/fonts/iconmagic/fonts_resources/README.md
src/ps/fonts/iconmagic/fonts_resources/index.html
src/ps/fonts/iconmagic/fonts_resources/styles.css
src/ps/fonts/iconmagic/fonts_resources/fonts/iconmagic.eot
src/ps/fonts/iconmagic/fonts_resources/fonts/iconmagic.svg
src/ps/fonts/iconmagic/fonts_resources/fonts/iconmagic.ttf
src/ps/fonts/iconmagic/fonts_resources/fonts/iconmagic.woff
src/ps/fonts/iconmagic/locales/manual.pot
src/ps/fonts/iconmagic/locales/plone.pot
src/ps/fonts/iconmagic/locales/ps.diazo.iconmagic.pot
src/ps/fonts/iconmagic/locales/en/LC_MESSAGES/ps.diazo.iconmagic.po
src/ps/fonts/iconmagic/profiles/default/browserlayer.xml
src/ps/fonts/iconmagic/profiles/default/cssregistry.xml
src/ps/fonts/iconmagic/profiles/default/metadata.xml
src/ps/fonts/iconmagic/profiles/default/psdiazoiconmagic_marker.txt
src/ps/fonts/iconmagic/profiles/uninstall/browserlayer.xml
src/ps/fonts/iconmagic/template_overrides/README
src/ps/fonts/iconmagic/tests/__init__.py
src/ps/fonts/iconmagic/tests/test_robot.py
src/ps/fonts/iconmagic/tests/test_setup.py
src/ps/fonts/iconmagic/tests/robot/keywords.robot
src/ps/fonts/iconmagic/tests/robot/test_setup.robot